chatllm/__init__.py
chatllm/closeai.py
chatllm/llm_test.py
chatllm/agents/MultiPrompt.py
chatllm/agents/__init__.py
chatllm/agents/glm_agent.py
chatllm/agents/search.py
chatllm/agi/__init__.py
chatllm/agi/common.py
chatllm/api/__init__.py
chatllm/api/app.py
chatllm/api/config.py
chatllm/api/datamodels.py
chatllm/api/openai_client.py
chatllm/api/sse_api.py
chatllm/api/test.py
chatllm/api/routers/__init__.py
chatllm/api/routers/all_chat_completions.py
chatllm/api/routers/all_chat_completions_.py
chatllm/api/routers/api.py
chatllm/api/routers/audio_speech.py
chatllm/api/routers/chat_all.py
chatllm/api/routers/chat_cf.py
chatllm/api/routers/chat_completions_ali.py
chatllm/api/routers/chat_completions_ali_.py
chatllm/api/routers/chat_completions_ark.py
chatllm/api/routers/chat_completions_ark_for_zang.py
chatllm/api/routers/chat_completions_copilot.py
chatllm/api/routers/chat_completions_extra.py
chatllm/api/routers/chat_completions_glm.py
chatllm/api/routers/chat_completions_gptall.py
chatllm/api/routers/chat_completions_kimi.py
chatllm/api/routers/chat_completions_rag.py
chatllm/api/routers/chat_completions_redirect.py
chatllm/api/routers/chat_completions_smooth.py
chatllm/api/routers/chat_completions_suno.py
chatllm/api/routers/chat_deeplx.py
chatllm/api/routers/chat_yuanbao.py
chatllm/api/routers/cocopilot.py
chatllm/api/routers/demo.py
chatllm/api/routers/embeddings.py
chatllm/api/routers/files.py
chatllm/api/routers/files_moonshot.py
chatllm/api/routers/files_moonshot_api.py
chatllm/api/routers/local_embeddings.py
chatllm/api/routers/models.py
chatllm/api/routers/multi_apikey.py
chatllm/api/routers/polling_openai_api_keys.py
chatllm/api/routers/smooth_completions.py
chatllm/api/routers/sse.py
chatllm/api/routers/utils.py
chatllm/api/routers/batches/__init__.py
chatllm/api/routers/batches/v1.py
chatllm/api/routers/files/__init__.py
chatllm/api/routers/files/batch_chatglm.py
chatllm/api/routers/files/file_extract_moonshot.py
chatllm/api/routers/files/files.py
chatllm-2024.6.19.13.24.49.dist-info/LICENSE
chatllm-2024.6.19.13.24.49.dist-info/METADATA
chatllm-2024.6.19.13.24.49.dist-info/WHEEL
chatllm-2024.6.19.13.24.49.dist-info/entry_points.txt
chatllm-2024.6.19.13.24.49.dist-info/top_level.txt
chatllm-2024.6.19.13.24.49.dist-info/RECORD
