Metadata-Version: 2.1
Name: chatllm
Version: 2024.6.19.13.24.49
Summary: Create a Python package.
Home-page: https://github.com/yuanjie-ai/ChatLLM
Author: yuanjie
Author-email: 313303303@qq.com
License: MIT license
Keywords: chatllm
Classifier: Development Status :: 2 - Pre-Alpha
Classifier: Intended Audience :: Developers
Classifier: License :: OSI Approved :: MIT License
Classifier: Natural Language :: English
Classifier: Programming Language :: Python :: 3.7
Classifier: Programming Language :: Python :: 3.8
Requires-Python: >=3.7
License-File: LICENSE
Requires-Dist: meutils
Requires-Dist: openai
Requires-Dist: tiktoken
Requires-Dist: langchain
Requires-Dist: transformers
Requires-Dist: sentence-transformers
Requires-Dist: tokenizers
Requires-Dist: accelerate
Requires-Dist: cpm-kernels
Provides-Extra: all
Requires-Dist: streamlit-chat ; extra == 'all'
Requires-Dist: sse-starlette ; extra == 'all'
Requires-Dist: streamlit ; extra == 'all'
Requires-Dist: minio ; extra == 'all'
Requires-Dist: redis ; extra == 'all'
Requires-Dist: pymupdf ; extra == 'all'
Requires-Dist: openai ; extra == 'all'
Requires-Dist: fastapi ; extra == 'all'
Requires-Dist: faiss-cpu ; extra == 'all'
Requires-Dist: qdrant-client ; extra == 'all'
Provides-Extra: ann
Requires-Dist: qdrant-client ; extra == 'ann'
Provides-Extra: api
Requires-Dist: openai ; extra == 'api'
Requires-Dist: fastapi ; extra == 'api'
Requires-Dist: sse-starlette ; extra == 'api'
Provides-Extra: openai
Requires-Dist: openai ; extra == 'openai'
Requires-Dist: fastapi ; extra == 'openai'
Requires-Dist: sse-starlette ; extra == 'openai'
Provides-Extra: pdf
Requires-Dist: pymupdf ; extra == 'pdf'
Requires-Dist: streamlit ; extra == 'pdf'
Requires-Dist: streamlit-chat ; extra == 'pdf'
Provides-Extra: rag
Requires-Dist: redis ; extra == 'rag'
Requires-Dist: minio ; extra == 'rag'
Requires-Dist: faiss-cpu ; extra == 'rag'
Provides-Extra: streamlit
Requires-Dist: streamlit ; extra == 'streamlit'
Requires-Dist: streamlit-chat ; extra == 'streamlit'
